<?xml version="1.0" encoding="UTF-8"?>
<pc:PcGts xmlns:pc="http://schema.primaresearch.org/PAGE/gts/pagecontent/2019-07-15" xmlns:xsi="http://www.w3.org/2001/XMLSchema-instance" xsi:schemaLocation="http://schema.primaresearch.org/PAGE/gts/pagecontent/2019-07-15 http://schema.primaresearch.org/PAGE/gts/pagecontent/2019-07-15/pagecontent.xsd" pcGtsId="OCR-D-BIN_0020">
    <pc:Metadata>
        <pc:Creator>Deutsches Textarchiv</pc:Creator>
        <pc:Created>2018-03-22T10:08:20</pc:Created>
        <pc:LastChange>2022-11-11T10:15:39</pc:LastChange>
        <pc:MetadataItem type="processingStep" name="preprocessing/optimization/binarization" value="ocrd-cis-ocropy-binarize">
            <pc:Labels externalModel="ocrd-tool" externalId="parameters">
                <pc:Label value="page" type="level-of-operation"/>
                <pc:Label value="ocropy" type="method"/>
                <pc:Label value="0.5" type="threshold"/>
                <pc:Label value="False" type="grayscale"/>
                <pc:Label value="0.0" type="maxskew"/>
                <pc:Label value="0" type="noise_maxsize"/>
                <pc:Label value="0" type="dpi"/>
            </pc:Labels>
            <pc:Labels externalModel="ocrd-tool" externalId="version">
                <pc:Label value="0.1.5" type="ocrd-cis-ocropy-binarize"/>
                <pc:Label value="2.52.0" type="ocrd/core"/>
            </pc:Labels>
        </pc:MetadataItem>
    </pc:Metadata>
    <pc:Page imageFilename="jpg/bebel_frau_1879_0188.jpg" imageWidth="1065" imageHeight="1633" orientation="0." type="content">
        <pc:AlternativeImage filename="OCR-D-BIN/OCR-D-BIN_0020.IMG-BIN.png" comments=",binarized"/>
    </pc:Page>
</pc:PcGts>
